isda_streaming/__init__.py
isda_streaming/data_stream.py
isda_streaming/py.typed
isda_streaming/synopsis.py
isda_streaming-1.2.0.dist-info/METADATA
isda_streaming-1.2.0.dist-info/WHEEL
isda_streaming-1.2.0.dist-info/licenses/LICENSE
isda_streaming-1.2.0.dist-info/RECORD
