Metadata-Version: 2.4
Name: isda-streaming
Version: 1.2.0
Summary: A light-weight streaming library for the ISDA course at TU Berlin.
Project-URL: Homepage, https://git.tu-berlin.de/dima/isda/isda-streaming
Project-URL: Repository, https://git.tu-berlin.de/dima/isda/isda-streaming
Author-email: Rudi Poepsel Lemaitre <r.poepsellemaitre@tu-berlin.de>, Lennart Behme <lennart.behme@tu-berlin.de>
Maintainer-email: ISDA Team <isda@dima.tu-berlin.de>
License-Expression: Apache-2.0
License-File: LICENSE
Keywords: data-streams
Classifier: License :: OSI Approved :: Apache Software License
Classifier: Programming Language :: Python :: 3.10
Classifier: Programming Language :: Python :: 3.11
Classifier: Programming Language :: Python :: 3.12
Classifier: Programming Language :: Python :: 3.13
Requires-Python: >=3.10
Requires-Dist: numpy<3,>=1.24
Provides-Extra: dev
Requires-Dist: pdoc~=15.0; extra == 'dev'
Requires-Dist: pre-commit~=4.0; extra == 'dev'
